gids/__init__.py
gids/builder.py
gids-1.2.2.dist-info/METADATA
gids-1.2.2.dist-info/WHEEL
gids-1.2.2.dist-info/top_level.txt
gids-1.2.2.dist-info/RECORD
